ArvoresDecisaoGPRL4/__init__.py
ArvoresDecisaoGPRL4/arvores.py
ArvoresDecisaoGPRL4/c45.py
ArvoresDecisaoGPRL4/cart.py
ArvoresDecisaoGPRL4/id3.py
arvoresdecisaogprl4-0.1.0.dist-info/LICENSE.txt
arvoresdecisaogprl4-0.1.0.dist-info/METADATA
arvoresdecisaogprl4-0.1.0.dist-info/WHEEL
arvoresdecisaogprl4-0.1.0.dist-info/top_level.txt
arvoresdecisaogprl4-0.1.0.dist-info/RECORD
